ws2x/__init__.py
ws2x/led.py
ws2x_vjsrinivas-0.0.2.dist-info/LICENSE
ws2x_vjsrinivas-0.0.2.dist-info/METADATA
ws2x_vjsrinivas-0.0.2.dist-info/WHEEL
ws2x_vjsrinivas-0.0.2.dist-info/top_level.txt
ws2x_vjsrinivas-0.0.2.dist-info/RECORD
