Metadata-Version: 2.1
Name: ws2x-vjsrinivas
Version: 0.0.2
Summary: A simple simulator for WS2812B-style LED strips
Home-page: https://github.com/vjsrinivas/ws2x-strip
Author: Vijay Rajagopal
Author-email: vijaythinks@gmail.com
License: UNKNOWN
Download-URL: https://github.com/vjsrinivas/ws2x-strip/archive/0.0.1.tar.gz
Platform: UNKNOWN
Classifier: Programming Language :: Python :: 3
Classifier: Topic :: Multimedia :: Graphics :: Editors :: Raster-Based
Classifier: Operating System :: OS Independent
Requires-Python: >=3.0
Requires-Dist: numpy
Requires-Dist: opencv-python
